{
  "generator-jhipster": {
    "promptValues": {
      "packageName": "com.gdp.jhipster",
      "nativeLanguage": "en"
    },
    "jhipsterVersion": "6.10.5",
    "applicationType": "monolith",
    "baseName": "gdpJhipster",
    "packageName": "com.gdp.jhipster",
    "packageFolder": "com/gdp/jhipster",
    "serverPort": "8080",
    "authenticationType": "session",
    "cacheProvider": "ehcache",
    "enableHibernateCache": true,
    "websocket": false,
    "databaseType": "sql",
    "devDatabaseType": "mysql",
    "prodDatabaseType": "mysql",
    "searchEngine": false,
    "messageBroker": false,
    "serviceDiscoveryType": false,
    "buildTool": "maven",
    "enableSwaggerCodegen": false,
    "rememberMeKey": "d22b8ca20c095df1ee20314622c116cc921ee703041c4547cdbb767e0a0be82a8da3f07659b82d1bc4c8b9881b54aec396a7",
    "embeddableLaunchScript": false,
    "useSass": true,
    "clientPackageManager": "npm",
    "clientFramework": "angularX",
    "clientTheme": "simplex",
    "clientThemeVariant": "dark",
    "creationTimestamp": 1614201815607,
    "testFrameworks": [],
    "jhiPrefix": "jhi",
    "entitySuffix": "",
    "dtoSuffix": "DTO",
    "otherModules": [],
    "enableTranslation": true,
    "nativeLanguage": "en",
    "languages": ["en"],
    "blueprints": []
  }
}
